pycaption/__init__.py
pycaption/base.py
pycaption/exceptions.py
pycaption/geometry.py
pycaption/microdvd.py
pycaption/sami.py
pycaption/srt.py
pycaption/transcript.py
pycaption/utils.py
pycaption/webvtt.py
pycaption/dfxp/__init__.py
pycaption/dfxp/base.py
pycaption/dfxp/extras.py
pycaption/scc/__init__.py
pycaption/scc/constants.py
pycaption/scc/specialized_collections.py
pycaption/scc/state_machines.py
pycaption/scc/translator.py
pycaption-2.2.19.dist-info/licenses/LICENSE
tests/__init__.py
tests/conftest.py
tests/mixins.py
tests/test_base.py
tests/test_dfxp.py
tests/test_dfxp_conversion.py
tests/test_dfxp_extras.py
tests/test_functions.py
tests/test_geometry.py
tests/test_microdvd.py
tests/test_microdvd_conversion.py
tests/test_sami.py
tests/test_sami_conversion.py
tests/test_scc.py
tests/test_scc_conversion.py
tests/test_scc_translator.py
tests/test_srt.py
tests/test_srt_conversion.py
tests/test_webvtt.py
tests/test_webvtt_conversion.py
tests/fixtures/__init__.py
tests/fixtures/dfxp.py
tests/fixtures/microdvd.py
tests/fixtures/sami.py
tests/fixtures/scc.py
tests/fixtures/srt.py
tests/fixtures/translated_scc.py
tests/fixtures/webvtt.py
pycaption-2.2.19.dist-info/METADATA
pycaption-2.2.19.dist-info/WHEEL
pycaption-2.2.19.dist-info/top_level.txt
pycaption-2.2.19.dist-info/RECORD
