Metadata-Version: 2.4
Name: pycaption
Version: 2.2.19
Summary: Closed caption converter
Author: Joe Norton
Author-email: joey@nortoncrew.com
Project-URL: Source, https://github.com/pbs/pycaption
Project-URL: Documentation, https://pycaption.readthedocs.io/
Project-URL: Release notes, https://pycaption.readthedocs.io/en/stable/changelog.html
Classifier: Development Status :: 5 - Production/Stable
Classifier: License :: OSI Approved :: Apache Software License
Classifier: Operating System :: OS Independent
Classifier: Programming Language :: Python
Classifier: Programming Language :: Python :: 3
Classifier: Programming Language :: Python :: 3.10
Classifier: Programming Language :: Python :: 3.11
Classifier: Programming Language :: Python :: 3.12
Classifier: Topic :: Software Development :: Libraries
Classifier: Topic :: Software Development :: Libraries :: Python Modules
Classifier: Topic :: Multimedia :: Video
Requires-Python: >=3.10,<4.0
License-File: LICENSE
Requires-Dist: beautifulsoup4>=4.12.1
Requires-Dist: lxml>=4.9.1
Requires-Dist: cssutils>=2.0.0
Provides-Extra: dev
Requires-Dist: pytest; extra == "dev"
Requires-Dist: pytest-lazy-fixture; extra == "dev"
Provides-Extra: transcript
Requires-Dist: nltk==3.9.1; extra == "transcript"
Dynamic: author
Dynamic: author-email
Dynamic: classifier
Dynamic: description
Dynamic: license-file
Dynamic: project-url
Dynamic: provides-extra
Dynamic: requires-dist
Dynamic: requires-python
Dynamic: summary
